{
    "status": 0,
    "msg": "ok",
    "data": [
        {
            "show_type": "single3",
            "data": {
                "img": "http://shihuoproxy.hupucdn.com/aHR0cDovL2ltZy5hbGljZG4uY29tL2ltZ2V4dHJhL2kyLzc2Mjg5NDcxNS9UQjJwRENRcXJ0bHB1RmpTc3BvWFhiY0RwWGFfISE3NjI4OTQ3MTUuanBn?imageView2/0/w/600/h/600/interlace/1%7cimageMogr2/format/jpg",
                "tag_name": "",
                "title": "Shinning Barre 网纱运动内衣",
                "intro": "美背交叉设计，网纱面料，超宽的下围在运动中给予足够支撑",
                "merchant": "淘宝",
                "price": "90",
                "href": "//www.shihuo.cn/sports/detail/31017.html?supplierId=165862&newsId=99570&img=http%3A%2F%2Fshihuoproxy.hupucdn.com%2FaHR0cDovL2ltZy5hbGljZG4uY29tL2ltZ2V4dHJhL2kyLzc2Mjg5NDcxNS9UQjJwRENRcXJ0bHB1RmpTc3BvWFhiY0RwWGFfISE3NjI4OTQ3MTUuanBn&sourceType=5",
                "param_str": "1495712410:2:",
                "zhiding": false,
                "item_id": "63554",
                "expose_key": "",
                "qk": "news_general"
            }
        },
        {
            "show_type": "single3",
            "data": {
                "img": "http://shihuoproxy.hupucdn.com/aHR0cDovL2ltZy5hbGljZG4uY29tL2ltZ2V4dHJhL2kyLzI1OTE1NDg5MDkvVEIyeUxjb2FzSEExMUJqeTBGaVhYY2tmVlhhXyEhMjU5MTU0ODkwOS5qcGc?imageView2/0/w/600/h/600/interlace/1%7cimageMogr2/format/jpg",
                "tag_name": "",
                "title": "XSPORTS MANLINGE 紧身上衣",
                "intro": "透气排汗，超强弹力，压缩肌肉，像你的第二层皮肤。多款多色，爱运动才与众不同",
                "merchant": "淘宝",
                "price": "69",
                "href": "//www.shihuo.cn/sports/detail/19007.html?supplierId=73641&newsId=99625&img=http%3A%2F%2Fshihuoproxy.hupucdn.com%2FaHR0cDovL2ltZy5hbGljZG4uY29tL2ltZ2V4dHJhL2kyLzI1OTE1NDg5MDkvVEIyeUxjb2FzSEExMUJqeTBGaVhYY2tmVlhhXyEhMjU5MTU0ODkwOS5qcGc&sourceType=5",
                "param_str": "1495712345:2:",
                "zhiding": false,
                "item_id": "63552",
                "expose_key": "",
                "qk": "news_general"
            }
        },
        {
            "show_type": "single3",
            "data": {
                "img": "http://shihuoproxy.hupucdn.com/aHR0cDovL2ltZy5hbGljZG4uY29tL2ltZ2V4dHJhL2kzL1RCMTVUeGRRVlhYWFhjblhYWFhYWFhYWFhYWF8hITAtaXRlbV9waWMuanBn?imageView2/0/w/600/h/600/interlace/1%7cimageMogr2/format/jpg",
                "tag_name": "",
                "title": "MishkaNYC拉斯维加斯打底裤",
                "intro": "满版的拉斯维加斯满印印花，针织面料设计，上身更加舒适。",
                "merchant": "天猫",
                "price": "398",
                "href": "//www.shihuo.cn/sports/detail/29319.html?supplierId=158994&newsId=97839&img=http%3A%2F%2Fshihuoproxy.hupucdn.com%2FaHR0cDovL2ltZy5hbGljZG4uY29tL2ltZ2V4dHJhL2kzL1RCMTVUeGRRVlhYWFhjblhYWFhYWFhYWFhYWF8hITAtaXRlbV9waWMuanBn&sourceType=3",
                "param_str": "1495711807:2:",
                "zhiding": false,
                "item_id": "63547",
                "expose_key": "",
                "qk": "news_general"
            }
        },
        {
            "show_type": "single3",
            "data": {
                "img": "http://shihuoproxy.hupucdn.com/aHR0cDovL3NoaWh1by5odXB1Y2RuLmNvbS9nb29kcy8yMDE3MDUvMjIyMy9jMWExNTcxZjljODAzMjZmY2RiN2M3NTAwNjU5OTA4Yy5qcGc?imageView2/0/w/600/h/600/interlace/1%7cimageMogr2/format/jpg",
                "tag_name": "",
                "title": "斯伯丁 篮球训练包",
                "intro": "篮球纹理PU皮革贴边结合织物设计，也能当做旅行包使用。",
                "merchant": "天猫",
                "price": "239",
                "href": "//www.shihuo.cn/sports/detail/30296.html?supplierId=162963&newsId=98965&img=http%3A%2F%2Fshihuoproxy.hupucdn.com%2FaHR0cDovL3NoaWh1by5odXB1Y2RuLmNvbS9nb29kcy8yMDE3MDUvMjIyMy9jMWExNTcxZjljODAzMjZmY2RiN2M3NTAwNjU5OTA4Yy5qcGc&sourceType=1",
                "param_str": "1495710904:2:",
                "zhiding": false,
                "item_id": "63546",
                "expose_key": "",
                "qk": "news_general"
            }
        },
        {
            "show_type": "single3",
            "data": {
                "img": "http://shihuoproxy.hupucdn.com/aHR0cDovL3NoaWh1by5odXB1Y2RuLmNvbS9nb29kcy8yMDE3MDUvMjIyMy9hMTU0YjJkYjJmMmUzOTc0ZDg1NWMwNmU4ZjgxZGE3OS5qcGc?imageView2/0/w/600/h/600/interlace/1%7cimageMogr2/format/jpg",
                "tag_name": "",
                "title": "adidas Originals Tubular Radial",
                "intro": "时尚之选，adidas Tubular Radial。",
                "merchant": "淘宝",
                "price": "599",
                "href": "//www.shihuo.cn/sports/detail/153.html?supplierId=162977&newsId=98977&img=http%3A%2F%2Fshihuoproxy.hupucdn.com%2FaHR0cDovL3NoaWh1by5odXB1Y2RuLmNvbS9nb29kcy8yMDE3MDUvMjIyMy9hMTU0YjJkYjJmMmUzOTc0ZDg1NWMwNmU4ZjgxZGE3OS5qcGc&sourceType=2",
                "param_str": "1495710009:2:",
                "zhiding": false,
                "item_id": "63540",
                "expose_key": "",
                "qk": "news_general"
            }
        },
        {
            "show_type": "single3",
            "data": {
                "img": "http://shihuoproxy.hupucdn.com/aHR0cDovL3NoaWh1by5odXB1Y2RuLmNvbS9nb29kcy8yMDE3MDUvMjUxMS9iNGYzMjVjM2Y5OTQ2NDQwYjA0ZDg5NjBkMDQ1OWRlMy5qcGc?imageView2/0/w/600/h/600/interlace/1%7cimageMogr2/format/jpg",
                "tag_name": "",
                "title": "Nike Hyperdunk Lux",
                "intro": "Flywire 飞线技术提升整体包裹性与贴合感，侧翼则取消了 Swoosh 设定",
                "merchant": "淘宝",
                "price": "599",
                "href": "//www.shihuo.cn/sports/detail/11894.html?supplierId=90183&newsId=99610&img=http%3A%2F%2Fshihuoproxy.hupucdn.com%2FaHR0cDovL3NoaWh1by5odXB1Y2RuLmNvbS9nb29kcy8yMDE3MDUvMjUxMS9iNGYzMjVjM2Y5OTQ2NDQwYjA0ZDg5NjBkMDQ1OWRlMy5qcGc&sourceType=1",
                "param_str": "1495709104:2:",
                "zhiding": false,
                "item_id": "63539",
                "expose_key": "",
                "qk": "news_general"
            }
        },
        {
            "show_type": "single3",
            "data": {
                "img": "http://shihuoproxy.hupucdn.com/aHR0cDovL2ltZy5hbGljZG4uY29tL2ltZ2V4dHJhL2kyL1RCMU5acXdRVlhYWFhhWmFGWFhYWFhYWFhYWF8hITAtaXRlbV9waWMuanBn?imageView2/0/w/600/h/600/interlace/1%7cimageMogr2/format/jpg",
                "tag_name": "",
                "title": "TCA 四袋束脚裤",
                "intro": "别具街头潮流魅力，裤身两侧设有工装口袋，增加整体层次感与实用性",
                "merchant": "淘宝",
                "price": "299",
                "href": "//www.shihuo.cn/sports/detail/29322.html?supplierId=158999&newsId=97842&img=http%3A%2F%2Fshihuoproxy.hupucdn.com%2FaHR0cDovL2ltZy5hbGljZG4uY29tL2ltZ2V4dHJhL2kyL1RCMU5acXdRVlhYWFhhWmFGWFhYWFhYWFhYWF8hITAtaXRlbV9waWMuanBn&sourceType=3",
                "param_str": "1495708208:2:",
                "zhiding": false,
                "item_id": "63536",
                "expose_key": "",
                "qk": "news_general"
            }
        },
        {
            "show_type": "single3",
            "data": {
                "img": "http://shihuoproxy.hupucdn.com/aHR0cDovL3NoaWh1by5odXB1Y2RuLmNvbS9nb29kcy8yMDE3MDUvMjUxMS8wMDdjNjU1NDhkYWQzNjAxZmYwNmZmZDE4ZmU1ZjAzZS5qcGc?imageView2/0/w/600/h/600/interlace/1%7cimageMogr2/format/jpg",
                "tag_name": "",
                "title": "九儿运动 女子7分运动裤",
                "intro": "显瘦的高腰宽松的7分运动裤，非常适合夏日的运动穿着，透气吸汗，速干清爽",
                "merchant": "淘宝",
                "price": "55",
                "href": "//www.shihuo.cn/sports/detail/31033.html?supplierId=165955&newsId=99602&img=http%3A%2F%2Fshihuoproxy.hupucdn.com%2FaHR0cDovL3NoaWh1by5odXB1Y2RuLmNvbS9nb29kcy8yMDE3MDUvMjUxMS8wMDdjNjU1NDhkYWQzNjAxZmYwNmZmZDE4ZmU1ZjAzZS5qcGc&sourceType=5",
                "param_str": "1495707906:2:",
                "zhiding": false,
                "item_id": "63534",
                "expose_key": "",
                "qk": "news_general"
            }
        },
        {
            "show_type": "single3",
            "data": {
                "img": "http://shihuoproxy.hupucdn.com/aHR0cDovL3NoaWh1by5odXB1Y2RuLmNvbS9nb29kcy8yMDE3MDUvMjUxMS8wZTlmYTI0NzNkMDczNzAxMDg1YTY2MDY1NjdkNGZlZi5qcGc?imageView2/0/w/600/h/600/interlace/1%7cimageMogr2/format/jpg",
                "tag_name": "",
                "title": "labrada pro8 超级蛋白粉",
                "intro": "8种优质蛋白，多种口味可口帮助吸收，增肌塑形，让睡眠中野增肌",
                "merchant": "天猫",
                "price": "278",
                "href": "//www.shihuo.cn/sports/detail/31026.html?supplierId=165885&newsId=99590&img=http%3A%2F%2Fshihuoproxy.hupucdn.com%2FaHR0cDovL3NoaWh1by5odXB1Y2RuLmNvbS9nb29kcy8yMDE3MDUvMjUxMS8wZTlmYTI0NzNkMDczNzAxMDg1YTY2MDY1NjdkNGZlZi5qcGc&sourceType=5",
                "param_str": "1495707185:2:",
                "zhiding": false,
                "item_id": "63530",
                "expose_key": "",
                "qk": "news_general"
            }
        },
        {
            "show_type": "single3",
            "data": {
                "img": "http://shihuoproxy.hupucdn.com/aHR0cDovL3NoaWh1by5odXB1Y2RuLmNvbS9nb29kcy8yMDE3MDUvMTQyMy84MTg1YWQyYzg2NmRkMDkyMTU1MDkyMDUzMjVkYzJiNC5qcGc?imageView2/0/w/600/h/600/interlace/1%7cimageMogr2/format/jpg",
                "tag_name": "",
                "title": "NIKE Flyknit Trainer Chukka",
                "intro": "NIKE Flyknit男子透气编织飞线跑步鞋",
                "merchant": "淘宝",
                "price": "485",
                "href": "//www.shihuo.cn/sports/detail/16658.html?supplierId=150881&newsId=96946&img=http%3A%2F%2Fshihuoproxy.hupucdn.com%2FaHR0cDovL3NoaWh1by5odXB1Y2RuLmNvbS9nb29kcy8yMDE3MDUvMTQyMy84MTg1YWQyYzg2NmRkMDkyMTU1MDkyMDUzMjVkYzJiNC5qcGc&sourceType=2",
                "param_str": "1495706409:2:",
                "zhiding": false,
                "item_id": "63528",
                "expose_key": "",
                "qk": "news_general"
            }
        },
        {
            "show_type": "single3",
            "data": {
                "img": "http://shihuoproxy.hupucdn.com/aHR0cDovL3NoaWh1by5odXB1Y2RuLmNvbS9nb29kcy8yMDE3MDUvMjMxOS81MTRkMDc2ODExNDY2YzdjODE2NzVjMTM3MGRjMmI0My5qcGc?imageView2/0/w/600/h/600/interlace/1%7cimageMogr2/format/jpg",
                "tag_name": "",
                "title": "Nike Air Max 2 Uptempo",
                "intro": "以全白鞋面和中底加持3M反光材料带来不一样的全新面貌",
                "merchant": "淘宝",
                "price": "928",
                "href": "//www.shihuo.cn/sports/detail/10996.html?supplierId=164144&newsId=99182&img=http%3A%2F%2Fshihuoproxy.hupucdn.com%2FaHR0cDovL3NoaWh1by5odXB1Y2RuLmNvbS9nb29kcy8yMDE3MDUvMjMxOS81MTRkMDc2ODExNDY2YzdjODE2NzVjMTM3MGRjMmI0My5qcGc&sourceType=1",
                "param_str": "1495705503:2:",
                "zhiding": false,
                "item_id": "63518",
                "expose_key": "",
                "qk": "news_general"
            }
        },
        {
            "show_type": "single3",
            "data": {
                "img": "http://shihuoproxy.hupucdn.com/aHR0cDovL2ltZy5hbGljZG4uY29tL2ltZ2V4dHJhL2kxLzc0OTEwODU2MC9UQjJ1RWJwdFhYWFhYYXRYWFhYWFhYWFhYWFhfISE3NDkxMDg1NjAuanBn?imageView2/0/w/600/h/600/interlace/1%7cimageMogr2/format/jpg",
                "tag_name": "",
                "title": "Masterape 打底衫",
                "intro": "宽松舒适版型设计，休闲百搭，纯白的选色更易穿出层次感",
                "merchant": "淘宝",
                "price": "88",
                "href": "//www.shihuo.cn/sports/detail/28322.html?supplierId=154188&newsId=96742&img=http%3A%2F%2Fshihuoproxy.hupucdn.com%2FaHR0cDovL2ltZy5hbGljZG4uY29tL2ltZ2V4dHJhL2kxLzc0OTEwODU2MC9UQjJ1RWJwdFhYWFhYYXRYWFhYWFhYWFhYWFhfISE3NDkxMDg1NjAuanBn&sourceType=3",
                "param_str": "1495704607:2:",
                "zhiding": false,
                "item_id": "63510",
                "expose_key": "",
                "qk": "news_general"
            }
        },
        {
            "show_type": "single3",
            "data": {
                "img": "http://shihuoproxy.hupucdn.com/aHR0cDovL3NoaWh1by5odXB1Y2RuLmNvbS9nb29kcy8yMDE3MDUvMTkyMC8xNjBlYmM2ZjNlZWU5MDg4NzVjYjljNGYxYWZiMjVlMi5qcGc?imageView2/0/w/600/h/600/interlace/1%7cimageMogr2/format/jpg",
                "tag_name": "",
                "title": "Nike Paul George PG1",
                "intro": "鞋身以黑色为主色调，鞋面魔术贴采用紫罗兰色",
                "merchant": "淘宝",
                "price": "999",
                "href": "//www.shihuo.cn/sports/detail/18368.html?supplierId=160825&newsId=98275&img=http%3A%2F%2Fshihuoproxy.hupucdn.com%2FaHR0cDovL3NoaWh1by5odXB1Y2RuLmNvbS9nb29kcy8yMDE3MDUvMTkyMC8xNjBlYmM2ZjNlZWU5MDg4NzVjYjljNGYxYWZiMjVlMi5qcGc&sourceType=1",
                "param_str": "1495703703:2:",
                "zhiding": false,
                "item_id": "63502",
                "expose_key": "",
                "qk": "news_general"
            }
        },
        {
            "show_type": "single3",
            "data": {
                "img": "http://shihuoproxy.hupucdn.com/aHR0cDovL3NoaWh1by5odXB1Y2RuLmNvbS9nb29kcy8yMDE3MDUvMTMyMi84MDcyMjQ0OTdkY2VlYmViMWUzMDNhYzE0ODFjZDljOC5wbmc?imageView2/0/w/600/h/600/interlace/1%7cimageMogr2/format/jpg",
                "tag_name": "",
                "title": "Mizuno  Wave Impetus 3",
                "intro": "Mizuno Wave Impetus 3，采用双层透气网面。",
                "merchant": "天猫",
                "price": "229",
                "href": "//www.shihuo.cn/sports/detail/9829.html?supplierId=154186&newsId=96740&img=http%3A%2F%2Fshihuoproxy.hupucdn.com%2FaHR0cDovL3NoaWh1by5odXB1Y2RuLmNvbS9nb29kcy8yMDE3MDUvMTMyMi84MDcyMjQ0OTdkY2VlYmViMWUzMDNhYzE0ODFjZDljOC5wbmc&sourceType=2",
                "param_str": "1495702808:2:",
                "zhiding": false,
                "item_id": "63499",
                "expose_key": "",
                "qk": "news_general"
            }
        },
        {
            "show_type": "single3",
            "data": {
                "img": "http://shihuoproxy.hupucdn.com/aHR0cDovL2ltZy5hbGljZG4uY29tL2ltZ2V4dHJhL2kyL1RCMUd2aGVRVlhYWFhiZ1hYWFhYWFhYWFhYWF8hITAtaXRlbV9waWMuanBn?imageView2/0/w/600/h/600/interlace/1%7cimageMogr2/format/jpg",
                "tag_name": "",
                "title": "MishkaNYC 字母印花八分裤",
                "intro": "迎合当下潮流采用八分裤设计，拉长你的双腿，裤腿出的字母印花设计",
                "merchant": "天猫",
                "price": "698",
                "href": "//www.shihuo.cn/sports/detail/29320.html?supplierId=158997&newsId=97840&img=http%3A%2F%2Fshihuoproxy.hupucdn.com%2FaHR0cDovL2ltZy5hbGljZG4uY29tL2ltZ2V4dHJhL2kyL1RCMUd2aGVRVlhYWFhiZ1hYWFhYWFhYWFhYWF8hITAtaXRlbV9waWMuanBn&sourceType=3",
                "param_str": "1495701007:2:",
                "zhiding": false,
                "item_id": "63493",
                "expose_key": "",
                "qk": "news_general"
            }
        },
        {
            "show_type": "single3",
            "data": {
                "img": "http://shihuoproxy.hupucdn.com/aHR0cDovL3NoaWh1by5odXB1Y2RuLmNvbS9nb29kcy8yMDE3MDUvMTgyMS85ZjQwNGU5OTdhYTRjMDFhMmM5MWRlYjY1OWMxN2NiMC5qcGc?imageView2/0/w/600/h/600/interlace/1%7cimageMogr2/format/jpg",
                "tag_name": "",
                "title": "Nike LeBron Soldier 10",
                "intro": "后跟搭载 Zoom Air 气垫，灵敏缓震三条固定带，打造专属的牢固贴合感",
                "merchant": "淘宝",
                "price": "499",
                "href": "//www.shihuo.cn/sports/detail/6972.html?supplierId=154017&newsId=98079&img=http%3A%2F%2Fshihuoproxy.hupucdn.com%2FaHR0cDovL3NoaWh1by5odXB1Y2RuLmNvbS9nb29kcy8yMDE3MDUvMTgyMS85ZjQwNGU5OTdhYTRjMDFhMmM5MWRlYjY1OWMxN2NiMC5qcGc&sourceType=1",
                "param_str": "1495700104:2:",
                "zhiding": false,
                "item_id": "63490",
                "expose_key": "",
                "qk": "news_general"
            }
        },
        {
            "show_type": "single3",
            "data": {
                "img": "http://shihuoproxy.hupucdn.com/aHR0cDovL3NoaWh1by5odXB1Y2RuLmNvbS9nb29kcy8yMDE3MDUvMjUxMS80MGE4NmJiODFiOGUzMjA3OTFmNWUxYWZmODA2YTc0ZC5qcGc?imageView2/0/w/600/h/600/interlace/1%7cimageMogr2/format/jpg",
                "tag_name": "",
                "title": "云端贝壳 薄纱运动T恤",
                "intro": "采用性感网纱拼接设计，性感中不失优雅，穿起来不仅透气",
                "merchant": "淘宝",
                "price": "49",
                "href": "//www.shihuo.cn/sports/detail/31025.html?supplierId=165881&newsId=99586&img=http%3A%2F%2Fshihuoproxy.hupucdn.com%2FaHR0cDovL3NoaWh1by5odXB1Y2RuLmNvbS9nb29kcy8yMDE3MDUvMjUxMS80MGE4NmJiODFiOGUzMjA3OTFmNWUxYWZmODA2YTc0ZC5qcGc&sourceType=5",
                "param_str": "1495699686:2:",
                "zhiding": false,
                "item_id": "63489",
                "expose_key": "",
                "qk": "news_general"
            }
        },
        {
            "show_type": "single3",
            "data": {
                "img": "http://shihuoproxy.hupucdn.com/aHR0cDovL3NoaWh1by5odXB1Y2RuLmNvbS9nb29kcy8yMDE3MDUvMTQyMi84ZjI2NWUyODQwMTRlOTJjZjliZjczMjc0MWU3MmMwMy5wbmc?imageView2/0/w/600/h/600/interlace/1%7cimageMogr2/format/jpg",
                "tag_name": "",
                "title": "Asics Gel-Contend 4",
                "intro": "舒适透气，专业简洁，Asics Gel-Contend 4。",
                "merchant": "天猫",
                "price": "360",
                "href": "//www.shihuo.cn/sports/detail/21390.html?supplierId=154424&newsId=96937&img=http%3A%2F%2Fshihuoproxy.hupucdn.com%2FaHR0cDovL3NoaWh1by5odXB1Y2RuLmNvbS9nb29kcy8yMDE3MDUvMTQyMi84ZjI2NWUyODQwMTRlOTJjZjliZjczMjc0MWU3MmMwMy5wbmc&sourceType=2",
                "param_str": "1495699208:2:",
                "zhiding": false,
                "item_id": "63488",
                "expose_key": "",
                "qk": "news_general"
            }
        },
        {
            "show_type": "single3",
            "data": {
                "img": "http://shihuoproxy.hupucdn.com/aHR0cDovL3NoaWh1by5odXB1Y2RuLmNvbS9nb29kcy8yMDE3MDUvMTYyMS9iZjY3ZDE1ZjliOGI4MzI5M2U4OWQxYmRjMDc4YzAzNy5qcGc?imageView2/0/w/600/h/600/interlace/1%7cimageMogr2/format/jpg",
                "tag_name": "",
                "title": "Air Jordan 31",
                "intro": "鞋身从前至后以黑色六边形织物自然过渡到鞋帮青绿染色皮革",
                "merchant": "淘宝",
                "price": "1349",
                "href": "//www.shihuo.cn/sports/detail/8340.html?supplierId=86745&newsId=97493&img=http%3A%2F%2Fshihuoproxy.hupucdn.com%2FaHR0cDovL3NoaWh1by5odXB1Y2RuLmNvbS9nb29kcy8yMDE3MDUvMTYyMS9iZjY3ZDE1ZjliOGI4MzI5M2U4OWQxYmRjMDc4YzAzNy5qcGc&sourceType=1",
                "param_str": "1495698304:2:",
                "zhiding": false,
                "item_id": "63483",
                "expose_key": "",
                "qk": "news_general"
            }
        },
        {
            "show_type": "single3",
            "data": {
                "img": "http://shihuoproxy.hupucdn.com/aHR0cDovL3NoaWh1by5odXB1Y2RuLmNvbS9nb29kcy8yMDE3MDUvMTUyMS8yYWM0MmE5OWJlOTlhMjk1N2RiNTZjN2Q1MGQwZWRkNC5qcGc?imageView2/0/w/600/h/600/interlace/1%7cimageMogr2/format/jpg",
                "tag_name": "",
                "title": "MOSTWANTEDLAB 牛津纺立领衬衫",
                "intro": "特意做了洗水工艺不用担心缩水，细条纹简约设计，拼色小细节，很实穿的一款衬衫",
                "merchant": "淘宝",
                "price": "208",
                "href": "//www.shihuo.cn/sports/detail/28667.html?supplierId=154989&newsId=97207&img=http%3A%2F%2Fshihuoproxy.hupucdn.com%2FaHR0cDovL3NoaWh1by5odXB1Y2RuLmNvbS9nb29kcy8yMDE3MDUvMTUyMS8yYWM0MmE5OWJlOTlhMjk1N2RiNTZjN2Q1MGQwZWRkNC5qcGc&sourceType=3",
                "param_str": "1495697407:2:",
                "zhiding": false,
                "item_id": "63480",
                "expose_key": "",
                "qk": "news_general"
            }
        }
    ],
    "missed": [],
    "youhui": [],
    "ad": {
        "qk": "recommend_ad"
    },
    "list_ad": []
}